uiuc_490_sp23/Constraints/__init__.py
uiuc_490_sp23/Exceptions/__init__.py
uiuc_490_sp23/LineSearch/__init__.py
uiuc_490_sp23/Optimizers/__init__.py
uiuc_490_sp23/Problem/__init__.py
uiuc_490_sp23/__init__.py
uiuc_490_sp23/__main__.py
uiuc_490_sp23/assignment1/Lab1_sp2023.pdf
uiuc_490_sp23/assignment1/__init__.py
uiuc_490_sp23/assignment1/__main__.py
uiuc_490_sp23/assignment2/__init__.py
uiuc_490_sp23/assignment2/__main__.py
uiuc_490_sp23/assignment2/asgn_source.py
uiuc_490_sp23/assignment2/newtons.py
uiuc_490_sp23/assignment2/projected_gd.py
uiuc_490_sp23/assignment3/__init__.py
uiuc_490_sp23/assignment3/__main__.py
uiuc_490_sp23-0.1.3.dist-info/WHEEL
uiuc_490_sp23-0.1.3.dist-info/entry_points.txt
uiuc_490_sp23-0.1.3.dist-info/METADATA
uiuc_490_sp23-0.1.3.dist-info/LICENSE
uiuc_490_sp23-0.1.3.dist-info/RECORD
