Metadata-Version: 2.1
Name: uiuc-490-sp23
Version: 0.1.3
Summary: Programming assignments for UIUC's ECE490: Introduction to Optimization course during Spring 2023
Home-page: https://github.com/eric-silk/ECE490
License: GPL-3.0-or-later
Keywords: optimization
Author: Eric Silk
Author-email: eric.silk@ericsilk.com
Requires-Python: >=3.10,<3.12
Classifier: Intended Audience :: Education
Classifier: License :: OSI Approved :: GNU General Public License v3 or later (GPLv3+)
Classifier: Natural Language :: English
Classifier: Operating System :: OS Independent
Classifier: Programming Language :: Python :: 3
Classifier: Programming Language :: Python :: 3.10
Classifier: Programming Language :: Python :: 3.11
Classifier: Programming Language :: Python :: 3 :: Only
Classifier: Topic :: Education
Classifier: Topic :: Scientific/Engineering :: Mathematics
Requires-Dist: matplotlib (>=3.7.1,<4.0.0)
Requires-Dist: numpy (>=1.24.2,<2.0.0)
Requires-Dist: scipy (>=1.10.1,<2.0.0)
Project-URL: Bug Tracker, https://github.com/eric-silk/ECE490/issues
Project-URL: Repository, https://github.com/eric-silk/ECE490
